model_registry_mlflow/__init__.py
model_registry_mlflow/api_client.py
model_registry_mlflow/auth.py
model_registry_mlflow/converters.py
model_registry_mlflow/operations/__init__.py
model_registry_mlflow/operations/experiment.py
model_registry_mlflow/operations/metric.py
model_registry_mlflow/operations/model.py
model_registry_mlflow/operations/run.py
model_registry_mlflow/operations/search.py
model_registry_mlflow/tracking_store.py
model_registry_mlflow/utils.py
model_registry_mlflow-0.0.1.dist-info/WHEEL
model_registry_mlflow-0.0.1.dist-info/entry_points.txt
model_registry_mlflow-0.0.1.dist-info/METADATA
model_registry_mlflow-0.0.1.dist-info/RECORD
