Metadata-Version: 2.4
Name: model-registry-mlflow
Version: 0.0.1
Summary: Kubeflow Model Registry MLflow Integration Plugin
Author: Dhiraj Bokde
Author-email: Dhiraj Bokde <<dhirajsb@users.noreply.github.com>>
License-Expression: Apache-2.0
Requires-Dist: mlflow>=2.0.0
Requires-Dist: requests>=2.25.0
Requires-Python: >=3.9
